Metadata-Version: 2.1
Name: hadoop-mapreduce
Version: 0.2
Summary: Implementation of Hadoop Mapreduce on text files
Home-page: https://github.com/dhruva1108/hadoop_mapreduce
Download-URL: https://github.com/dhruva1108/hadoop_mapreduce/archive/refs/tags/0.2.tar.gz
Author: Dhruva Sundararajan
Author-email: dhruva.sundararajan@gmail.com
License: MIT
Keywords: hadoop,mapreduce,hdfs
Classifier: Development Status :: 3 - Alpha
Classifier: Intended Audience :: Developers
Classifier: Topic :: Software Development :: Build Tools
Classifier: License :: OSI Approved :: MIT License
Classifier: Programming Language :: Python :: 3
Classifier: Programming Language :: Python :: 3.4
Classifier: Programming Language :: Python :: 3.5
Classifier: Programming Language :: Python :: 3.6
Classifier: Programming Language :: Python :: 3.7
Classifier: Programming Language :: Python :: 3.8
Classifier: Programming Language :: Python :: 3.9
Classifier: Programming Language :: Python :: 3.10
License-File: LICENSE.txt
